traffic_replay/RandomReplay.py
traffic_replay/Scheduler.py
traffic_replay/WorkerTask.py
traffic_replay/__init__.py
traffic_replay/__main__.py
traffic_replay/extractHeader.py
traffic_replay/glb.py
traffic_replay/h1Replay.py
traffic_replay/h2Replay.py
traffic_replay/mainProcess.py
traffic_replay/replay.py
traffic_replay/sanitizer.py
traffic_replay-1.0.0.dist-info/LICENSE
traffic_replay-1.0.0.dist-info/METADATA
traffic_replay-1.0.0.dist-info/NOTICE
traffic_replay-1.0.0.dist-info/WHEEL
traffic_replay-1.0.0.dist-info/entry_points.txt
traffic_replay-1.0.0.dist-info/top_level.txt
traffic_replay-1.0.0.dist-info/RECORD
